pyipatool/README.md
pyipatool/__init__.py
pyipatool/config.py
pyipatool/cookie_jar.py
pyipatool/http_client.py
pyipatool/main.py
pyipatool/models.py
pyipatool/api/__init__.py
pyipatool/api/auth.py
pyipatool/api/download.py
pyipatool/api/get_version_metadata.py
pyipatool/api/list_version.py
pyipatool/api/lookup.py
pyipatool/api/search.py
pyipatool/data/config.json.example
pyipatool-1.0.7.dist-info/METADATA
pyipatool-1.0.7.dist-info/WHEEL
pyipatool-1.0.7.dist-info/entry_points.txt
pyipatool-1.0.7.dist-info/top_level.txt
pyipatool-1.0.7.dist-info/RECORD
