Metadata-Version: 2.4
Name: pyipatool
Version: 1.0.7
Summary: Apple App Store search and download tool
Home-page: https://github.com/a55509432/pyipatool
Author: pjp
Author-email: pjp <pjp385334338@gmail.com>
License-Expression: MIT
Classifier: Programming Language :: Python :: 3
Classifier: Operating System :: OS Independent
Requires-Python: >=3.7
Requires-Dist: requests
Requires-Dist: click
Requires-Dist: pyyaml
Dynamic: author
Dynamic: home-page
Dynamic: requires-python
